setup.py
vals.py
vals.egg-info/PKG-INFO
vals.egg-info/SOURCES.txt
vals.egg-info/dependency_links.txt
vals.egg-info/not-zip-safe
vals.egg-info/requires.txt
vals.egg-info/top_level.txt