Metadata-Version: 1.0
Name: vals
Version: 0.0.1
Summary: value-stream processing
Home-page: https://github.com/tengu/vals
Author: karasuyamatengu
Author-email: karasuyamatengu@gmail.com
License: LGPL
Platform: UNKNOWN
